ili934x.py
setup.py
micropython_ili934x.egg-info/PKG-INFO
micropython_ili934x.egg-info/SOURCES.txt
micropython_ili934x.egg-info/dependency_links.txt
micropython_ili934x.egg-info/top_level.txt