Metadata-Version: 1.1
Name: micropython-ili934x
Version: 0.1.0
Summary: MicroPython SPI driver for ILI934X based displays
Home-page: https://github.com/tuupola/micropython-ili934x
Author: Mika Tuupola
Author-email: tuupola@appelsiini.net
License: MIT
Keywords: micropython tft lcd
Platform: UNKNOWN
Classifier: Development Status :: 2 - Pre-Alpha
Classifier: Programming Language :: Python :: Implementation :: MicroPython
Classifier: License :: OSI Approved :: MIT License
